QuantOPT/__init__.py
QuantOPT/conf/__init__.py
QuantOPT/conf/conf.py
QuantOPT/conf/conswriter.py
QuantOPT/conf/default_constraints.yaml
QuantOPT/constraints/__init__.py
QuantOPT/constraints/constraints.py
QuantOPT/constraints/relaxer.py
QuantOPT/core/__init__.py
QuantOPT/core/base.py
QuantOPT/core/model_core.py
QuantOPT/models/__init__.py
QuantOPT/models/model_MVO.py
QuantOPT/models/model_MaxIR.py
QuantOPT/models/model_MaxRiskAdjReturn.py
QuantOPT/models/model_MinVar.py
QuantOPT/models/model_RiskParity.py
QuantOPT/utils/__init__.py
QuantOPT/utils/boost_up.py
QuantOPT/utils/cached_property.py
QuantOPT/utils/chunk.py
QuantOPT/utils/file_cache.py
QuantOPT/utils/lazy_load.py
QuantOPT/utils/o_server.py
QuantOPT/utils/parse_rfc_1738_args.py
QuantOPT/utils/process_bar.py
QuantOPT/utils/singleton.py
QuantOPT/utils/uuid_generator.py
test/__init__.py
test/test_main_func.py
QuantOPT-0.1.1.8.dist-info/LICENSE
QuantOPT-0.1.1.8.dist-info/METADATA
QuantOPT-0.1.1.8.dist-info/WHEEL
QuantOPT-0.1.1.8.dist-info/top_level.txt
QuantOPT-0.1.1.8.dist-info/RECORD
