Metadata-Version: 2.1
Name: QuantOPT
Version: 0.1.1.8
Summary: a opt tool
Home-page: http://www.github.com/sn0wfree/QuantOPT
Author: sn0wfree
Author-email: snowfreedom0815@gmail.com
License: MIT Licence
Keywords: QuantOPT,analysis
Platform: UNKNOWN
